dnsdefender/__init__.py
dnsdefender/cli.py
dnsdefender/scan.py
dnsdefender/version.py
dnsdefender/aws/ec2.py
dnsdefender/aws/eips.py
dnsdefender/aws/globalaccelerator.py
dnsdefender/aws/lb.py
dnsdefender/aws/route53.py
dnsdefender/cloudFlare/records.py
dnsdefender/utils/constants.py
dnsdefender/utils/filters.py
dnsdefender/utils/old_dns_entries.py
dnsdefender/utils/result.py
dnsdefender/utils/takeover.py
dnsdefender/utils/whitelist.py
dnsdefender-1.0.3.dist-info/LICENSE
dnsdefender-1.0.3.dist-info/METADATA
dnsdefender-1.0.3.dist-info/WHEEL
dnsdefender-1.0.3.dist-info/entry_points.txt
dnsdefender-1.0.3.dist-info/top_level.txt
dnsdefender-1.0.3.dist-info/RECORD
