Metadata-Version: 2.1
Name: dnsdefender
Version: 1.0.3
Summary: Eliminate dangling elastic IPs by performing analysis on your resources within all your AWS accounts.
Home-page: https://gitlab.urbanclap.com/urbanclap/dangling-dns-service
Download-URL: https://github.com/assetnote/dnsdefender/archive/1.0.3.tar.gz
Author: pradhumanbaid
Author-email: pradhumansinghbaid@gmail.com
License: Apache Software License 2.0
Classifier: Development Status :: 3 - Alpha
Classifier: Intended Audience :: Developers
Classifier: Topic :: Software Development :: Libraries
Classifier: Programming Language :: Python :: 3.8
Requires-Python: >=0.0.1
License-File: LICENSE
Requires-Dist: click <9.0,>=8.0.3
Requires-Dist: boto3 ==1.23.10
Requires-Dist: cloudflare
Requires-Dist: awsipranges
Requires-Dist: slack-sdk
Requires-Dist: botocore <1.26.102
Requires-Dist: ipaddress
